backspace/__init__.py
backspace/backspace.py
backspace/kv.py
backspace-0.0.2.dist-info/METADATA
backspace-0.0.2.dist-info/WHEEL
backspace-0.0.2.dist-info/top_level.txt
backspace-0.0.2.dist-info/RECORD
